sfinx/__init__.py
sfinx/cli_tool.py
sfinx/version.py
sfinx-0.0.1.dev1.dist-info/METADATA
sfinx-0.0.1.dev1.dist-info/WHEEL
sfinx-0.0.1.dev1.dist-info/entry_points.txt
sfinx-0.0.1.dev1.dist-info/top_level.txt
sfinx-0.0.1.dev1.dist-info/RECORD
